.gitignore
MANIFEST.in
requirements.txt
setup.py
examples/album.py
examples/artist.py
examples/collection.py
examples/explore.py
examples/playlists.py
examples/restrictions.py
examples/search.py
examples/streaming_server/__init__.py
examples/streaming_server/dispatcher.py
examples/streaming_server/server.py
examples/streaming_server/track_reference.py
examples/streaming_server/util.py
examples/streaming_server/templates/album.html
spotify/__init__.py
spotify/client.py
spotify.py.egg-info/PKG-INFO
spotify.py.egg-info/SOURCES.txt
spotify.py.egg-info/dependency_links.txt
spotify.py.egg-info/requires.txt
spotify.py.egg-info/top_level.txt
spotify/commands/__init__.py
spotify/commands/base.py
spotify/commands/flash.py
spotify/commands/manager.py
spotify/commands/work.py
spotify/components/__init__.py
spotify/components/authentication.py
spotify/components/base.py
spotify/components/connection.py
spotify/components/explore.py
spotify/components/manager.py
spotify/components/metadata.py
spotify/components/search.py
spotify/core/__init__.py
spotify/core/helpers.py
spotify/core/request.py
spotify/core/revent.py
spotify/core/search_request.py
spotify/core/search_response.py
spotify/core/uri.py
spotify/hermes/__init__.py
spotify/hermes/cache.py
spotify/hermes/request.py
spotify/mercury/__init__.py
spotify/mercury/request.py
spotify/objects/__init__.py
spotify/objects/album.py
spotify/objects/album_group.py
spotify/objects/artist.py
spotify/objects/audio_file.py
spotify/objects/base.py
spotify/objects/copyright.py
spotify/objects/disc.py
spotify/objects/external_id.py
spotify/objects/image.py
spotify/objects/image_group.py
spotify/objects/parser.py
spotify/objects/playlist.py
spotify/objects/restriction.py
spotify/objects/top_tracks.py
spotify/objects/track.py
spotify/objects/user.py
spotify/proto/__init__.py
spotify/proto/bartender.proto
spotify/proto/bartender_pb2.py
spotify/proto/mercury.proto
spotify/proto/mercury_pb2.py
spotify/proto/metadata.proto
spotify/proto/metadata_pb2.py
spotify/proto/playlist4changes.proto
spotify/proto/playlist4changes_pb2.py
spotify/proto/playlist4content.proto
spotify/proto/playlist4content_pb2.py
