Metadata-Version: 1.1
Name: spotify.py
Version: 0.8.4
Summary: Python library to communicate with the Spotify WebSocket API
Home-page: https://github.com/fuzeman/spotify.py
Author: Dean Gardiner
Author-email: me@dgardiner.net
License: UNKNOWN
Platform: any
Classifier: Development Status :: 4 - Beta
Classifier: Intended Audience :: Developers
Classifier: Operating System :: OS Independent
Classifier: Programming Language :: Python
